paradigma/__init__.py
paradigma/assets/gait_detection_clf_package.pkl
paradigma/assets/gait_filtering_clf_package.pkl
paradigma/assets/ppg_quality_clf_package.pkl
paradigma/assets/tremor_detection_clf_package.pkl
paradigma/classification.py
paradigma/config.py
paradigma/constants.py
paradigma/feature_extraction.py
paradigma/pipelines/__init__.py
paradigma/pipelines/gait_pipeline.py
paradigma/pipelines/pulse_rate_pipeline.py
paradigma/pipelines/pulse_rate_utils.py
paradigma/pipelines/tremor_pipeline.py
paradigma/preprocessing.py
paradigma/segmenting.py
paradigma/testing.py
paradigma/util.py
paradigma-1.0.4.dist-info/METADATA
paradigma-1.0.4.dist-info/WHEEL
paradigma-1.0.4.dist-info/entry_points.txt
paradigma-1.0.4.dist-info/licenses/LICENSE
paradigma-1.0.4.dist-info/RECORD
