Metadata-Version: 2.4
Name: paradigma
Version: 1.0.4
Summary: ParaDigMa - A toolbox for deriving Parkinson's disease Digital Markers from real-life wrist sensor data
License: Apache-2.0
License-File: LICENSE
Author: Erik Post
Author-email: erik.post@radboudumc.nl
Requires-Python: >=3.11,<4.0
Classifier: License :: OSI Approved :: Apache Software License
Classifier: Programming Language :: Python :: 3
Classifier: Programming Language :: Python :: 3.11
Classifier: Programming Language :: Python :: 3.12
Classifier: Programming Language :: Python :: 3.13
Classifier: Programming Language :: Python :: 3.14
Requires-Dist: nbconvert (>=7.16.6,<8.0.0)
Requires-Dist: pandas (>=2.1.4,<3.0.0)
Requires-Dist: python-dateutil (>=2.9.0.post0,<3.0.0)
Requires-Dist: pytype (>=2024.4.11,<2025.0.0)
Requires-Dist: scikit-learn (>=1.3.2,<1.6.1)
Requires-Dist: tsdf (>=0.5.2,<0.6.0)
